pyaes/AES.py
pyaes/AESCore.py
pyaes/Field.py
pyaes/Key.py
pyaes/__init__.py
tests/AESCore_Test.py
tests/AES_Test.py
tests/Field_Test.py
tests/Key_Test.py
tests/__init__.py
ech2901_pyaes-1.2.4.dist-info/LICENSE
ech2901_pyaes-1.2.4.dist-info/METADATA
ech2901_pyaes-1.2.4.dist-info/WHEEL
ech2901_pyaes-1.2.4.dist-info/top_level.txt
ech2901_pyaes-1.2.4.dist-info/RECORD
