Metadata-Version: 2.1
Name: ech2901-pyaes
Version: 1.2.4
Summary: Python implementatoin of the AES Encryption Algorithm
Home-page: https://github.com/ech2901/pyaes
Author: Ellis Harlan
Author-email: EllisCHarlan@gmail.com
License: UNKNOWN
Platform: UNKNOWN
Classifier: Programming Language :: Python :: 3
Classifier: Programming Language :: Python :: 3.7
Classifier: Intended Audience :: Developers
Requires-Python: >=3.7
License-File: LICENSE
